CHANGES.rst
CONTRIBUTORS.rst
MANIFEST.in
README.rst
bootstrap.py
buildout.cfg
setup.py
cpskin/__init__.py
cpskin.diazotheme.newDream.egg-info/PKG-INFO
cpskin.diazotheme.newDream.egg-info/SOURCES.txt
cpskin.diazotheme.newDream.egg-info/dependency_links.txt
cpskin.diazotheme.newDream.egg-info/entry_points.txt
cpskin.diazotheme.newDream.egg-info/namespace_packages.txt
cpskin.diazotheme.newDream.egg-info/not-zip-safe
cpskin.diazotheme.newDream.egg-info/requires.txt
cpskin.diazotheme.newDream.egg-info/top_level.txt
cpskin/diazotheme/__init__.py
cpskin/diazotheme/newDream/__init__.py
cpskin/diazotheme/newDream/configure.zcml
cpskin/diazotheme/newDream/interfaces.py
cpskin/diazotheme/newDream/profiles.zcml
cpskin/diazotheme/newDream/upgradehandlers.py
cpskin/diazotheme/newDream/browser/__init__.py
cpskin/diazotheme/newDream/browser/configure.zcml
cpskin/diazotheme/newDream/browser/controlpanel.py
cpskin/diazotheme/newDream/browser/diazo.py
cpskin/diazotheme/newDream/browser/event_view.pt
cpskin/diazotheme/newDream/browser/event_view.py
cpskin/diazotheme/newDream/profiles/default/browserlayer.xml
cpskin/diazotheme/newDream/profiles/default/cssregistry.xml
cpskin/diazotheme/newDream/profiles/default/jsregistry.xml
cpskin/diazotheme/newDream/profiles/default/lessregistry.xml
cpskin/diazotheme/newDream/profiles/default/metadata.xml
cpskin/diazotheme/newDream/profiles/default/registry.xml
cpskin/diazotheme/newDream/profiles/default/theme.xml
cpskin/diazotheme/newDream/profiles/default/viewlets.xml
cpskin/diazotheme/newDream/profiles/uninstall/browserlayer.xml
cpskin/diazotheme/newDream/profiles/uninstall/cssregistry.xml
cpskin/diazotheme/newDream/profiles/uninstall/jsregistry.xml
cpskin/diazotheme/newDream/profiles/uninstall/lessregistry.xml
cpskin/diazotheme/newDream/static/manifest.cfg
cpskin/diazotheme/newDream/static/next.svg
cpskin/diazotheme/newDream/static/pause.svg
cpskin/diazotheme/newDream/static/play.svg
cpskin/diazotheme/newDream/static/prev.svg
cpskin/diazotheme/newDream/static/preview.png
cpskin/diazotheme/newDream/static/rules.xml
cpskin/diazotheme/newDream/static/css/menu_mobile_newdream.css
cpskin/diazotheme/newDream/static/css/menu_newdream.css
cpskin/diazotheme/newDream/static/css/styles.css
cpskin/diazotheme/newDream/static/fragments/search.pt
cpskin/diazotheme/newDream/static/js/ScrollMagic.min.js
cpskin/diazotheme/newDream/static/js/TweenMax.min.js
